edgegallery_sdk_mep/__init__.py
edgegallery_sdk_mep/api_client.py
edgegallery_sdk_mep/configuration.py
edgegallery_sdk_mep/rest.py
edgegallery_sdk_mep/api/__init__.py
edgegallery_sdk_mep/api/app_services_api.py
edgegallery_sdk_mep/api/app_subscriptions_api.py
edgegallery_sdk_mep/api/services_api.py
edgegallery_sdk_mep/api/token_api.py
edgegallery_sdk_mep/models/__init__.py
edgegallery_sdk_mep/models/category_ref.py
edgegallery_sdk_mep/models/category_ref_href.py
edgegallery_sdk_mep/models/category_ref_id.py
edgegallery_sdk_mep/models/category_ref_name.py
edgegallery_sdk_mep/models/category_ref_version.py
edgegallery_sdk_mep/models/category_refs.py
edgegallery_sdk_mep/models/empty.py
edgegallery_sdk_mep/models/end_point_info_address.py
edgegallery_sdk_mep/models/end_point_info_address_host.py
edgegallery_sdk_mep/models/end_point_info_address_port.py
edgegallery_sdk_mep/models/end_point_info_addresses.py
edgegallery_sdk_mep/models/end_point_info_alternative.py
edgegallery_sdk_mep/models/end_point_info_uri.py
edgegallery_sdk_mep/models/end_point_info_uris.py
edgegallery_sdk_mep/models/href.py
edgegallery_sdk_mep/models/link_type.py
edgegallery_sdk_mep/models/locality_type.py
edgegallery_sdk_mep/models/mec_service_mgmt_api_subscription_link_list.py
edgegallery_sdk_mep/models/mec_service_mgmt_api_subscription_link_list_links.py
edgegallery_sdk_mep/models/mec_service_mgmt_api_subscription_link_list_subscription.py
edgegallery_sdk_mep/models/model_self.py
edgegallery_sdk_mep/models/one_of_service_info_post.py
edgegallery_sdk_mep/models/one_of_transport_info_endpoint.py
edgegallery_sdk_mep/models/problem_detail.py
edgegallery_sdk_mep/models/problem_details.py
edgegallery_sdk_mep/models/problem_instance.py
edgegallery_sdk_mep/models/problem_status.py
edgegallery_sdk_mep/models/problem_title.py
edgegallery_sdk_mep/models/problem_type.py
edgegallery_sdk_mep/models/security_info.py
edgegallery_sdk_mep/models/security_info_o_auth2_info.py
edgegallery_sdk_mep-1.1.dist-info/METADATA
edgegallery_sdk_mep-1.1.dist-info/WHEEL
edgegallery_sdk_mep-1.1.dist-info/top_level.txt
edgegallery_sdk_mep-1.1.dist-info/RECORD
