Metadata-Version: 2.1
Name: edgegallery-sdk-mep
Version: 1.1
Summary: EdgeGallery MEC Service Management API
Home-page: UNKNOWN
Author: UNKNOWN
Author-email: UNKNOWN
License: UNKNOWN
Keywords: Swagger,EdgeGallery MEC Service Management API
Platform: UNKNOWN
Requires-Dist: urllib3 (>=1.15)
Requires-Dist: six (>=1.10)
Requires-Dist: certifi
Requires-Dist: python-dateutil
